README.md
setup.py
htmcatalog/__init__.py
htmcatalog/htmquery.py
htmcatalog.egg-info/PKG-INFO
htmcatalog.egg-info/SOURCES.txt
htmcatalog.egg-info/dependency_links.txt
htmcatalog.egg-info/top_level.txt