Metadata-Version: 1.2
Name: htmcatalog
Version: 0.1.1
Summary: htmcatalog: Hierarchical Triangular Mesh Catalogs
Home-page: https://github.com/MickaelRigault/htmcatalog/
Author: Mickael Rigault
Author-email: m.rigault@ipnl.in2p3.fr
Maintainer: Mickael Rigault
Maintainer-email: m.rigault@ipnl.in2p3.fr
License: BSD (3-clause)
Download-URL: https://github.com/MickaelRigault/htmcatalog/tarball/0.1
Platform: UNKNOWN
Classifier: Intended Audience :: Science/Research
Classifier: Programming Language :: Python :: 2.7
Classifier: Programming Language :: Python :: 3.5
Classifier: License :: OSI Approved :: BSD License
Classifier: Topic :: Scientific/Engineering :: Astronomy
Classifier: Operating System :: POSIX
Classifier: Operating System :: Unix
Classifier: Operating System :: MacOS
